{"trial_id": "015", "hyperparameters": {"space": [{"class_name": "Choice", "config": {"name": "optimizer", "default": "adam", "conditions": [], "values": ["adam", "sgd", "rmsprop"], "ordered": false}}, {"class_name": "Choice", "config": {"name": "learning_rate", "default": 0.1, "conditions": [], "values": [0.1, 0.01, 0.001], "ordered": true}}, {"class_name": "Choice", "config": {"name": "activation", "default": "relu", "conditions": [], "values": ["relu", "sigmoid"], "ordered": false}}, {"class_name": "Choice", "config": {"name": "layerconf", "default": "basic", "conditions": [], "values": ["basic", "denseAvg", "avgDense"], "ordered": false}}], "values": {"optimizer": "rmsprop", "learning_rate": 0.1, "activation": "relu", "layerconf": "denseAvg"}}, "metrics": {"metrics": {"loss": {"direction": "min", "observations": [{"value": [1.8448787927627563], "step": 15}]}, "accuracy": {"direction": "max", "observations": [{"value": [0.6432819366455078], "step": 15}]}, "val_loss": {"direction": "min", "observations": [{"value": [10.817091941833496], "step": 15}]}, "val_accuracy": {"direction": "max", "observations": [{"value": [0.0057234433479607105], "step": 15}]}}}, "score": 10.817091941833496, "best_step": 15, "status": "COMPLETED", "message": null}